[{"aqi":78,"area":"成都","pm2_5":44,"pm2_5_24h":null,"position_name":"金泉两河","primary_pollutant":null,"quality":"良","station_code":"1431A","time_point":"2013-11-04T22:00:00Z"},{"aqi":69,"area":"成都","pm2_5":53,"pm2_5_24h":null,"position_name":"十里店","primary_pollutant":null,"quality":"良","station_code":"1432A","time_point":"2013-11-04T22:00:00Z"},{"aqi":77,"area":"成都","pm2_5":48,"pm2_5_24h":null,"position_name":"三瓦窑","primary_pollutant":null,"quality":"良","station_code":"1433A","time_point":"2013-11-04T22:00:00Z"},{"aqi":74,"area":"成都","pm2_5":48,"pm2_5_24h":null,"position_name":"沙河铺","primary_pollutant":null,"quality":"良","station_code":"1434A","time_point":"2013-11-04T22:00:00Z"},{"aqi":62,"area":"成都","pm2_5":44,"pm2_5_24h":null,"position_name":"梁家巷","primary_pollutant":null,"quality":"良","station_code":"1435A","time_point":"2013-11-04T22:00:00Z"},{"aqi":65,"area":"成都","pm2_5":47,"pm2_5_24h":null,"position_name":"草堂寺","primary_pollutant":null,"quality":"良","station_code":"1436A","time_point":"2013-11-04T22:00:00Z"},{"aqi":74,"area":"成都","pm2_5":61,"pm2_5_24h":null,"position_name":"人民公园","primary_pollutant":null,"quality":"良","station_code":"1437A","time_point":"2013-11-04T22:00:00Z"},{"aqi":68,"area":"成都","pm2_5":63,"pm2_5_24h":null,"position_name":"灵岩寺","primary_pollutant":null,"quality":"良","station_code":"1438A","time_point":"2013-11-04T22:00:00Z"}]